[
  {
    "question": "Explain the architecture of the 80386 microprocessor with diagram.",
    "subject": "Computer organization and microprocessor",
    "type": "PYQ",
    "years": [2023, 2024],
    "frequency": 3,
    "tags": ["80386", "architecture"]
  },
  {
    "question": "Explain various addressing modes of 80386 with examples.",
    "subject": "Computer organization and microprocessor",
    "type": "PYQ",
    "years": [2023, 2024],
    "frequency": 5,
    "tags": ["addressing modes", "80386"]
  },
  {
    "question": "Explain data movement instructions of 80386 with examples.",
    "subject": "Computer organization and microprocessor",
    "type": "PYQ",
    "years": [2023, 2024],
    "frequency": 2,
    "tags": ["instructions", "data movement"]
  },
  {
    "question": "Explain operating modes of 80386.",
    "subject": "Computer organization and microprocessor",
    "type": "PYQ",
    "years": [2023],
    "frequency": 1,
    "tags": ["operating modes"]
  },
  {
    "question": "Explain general and segment registers of 80386.",
    "subject": "Computer organization and microprocessor",
    "type": "PYQ",
    "years": [2023],
    "frequency": 1,
    "tags": ["registers"]
  },
  {
    "question": "Explain processor state after reset in 80386.",
    "subject": "Computer organization and microprocessor",
    "type": "PYQ",
    "years": [2023, 2024],
    "frequency": 2,
    "tags": ["reset state"]
  },
  {
    "question": "Explain read and write cycles with non-pipelined timing.",
    "subject": "Computer organization and microprocessor",
    "type": "PYQ",
    "years": [2023, 2024],
    "frequency": 4,
    "tags": ["timing diagram"]
  },
  {
    "question": "Explain control registers of 80386.",
    "subject": "Computer organization and microprocessor",
    "type": "PYQ",
    "years": [2023, 2024],
    "frequency": 2,
    "tags": ["control registers"]
  },
  {
    "question": "Explain signals of 80386.",
    "subject": "Computer organization and microprocessor",
    "type": "PYQ",
    "years": [2023, 2024],
    "frequency": 2,
    "tags": ["signals"]
  },
  {
    "question": "Explain page translation process in 80386.",
    "subject": "Computer organization and microprocessor",
    "type": "PYQ",
    "years": [2022, 2023, 2024, 2025],
    "frequency": 8,
    "tags": ["paging", "memory management"]
  },
  {
    "question": "Explain segment translation process in 80386.",
    "subject": "Computer organization and microprocessor",
    "type": "PYQ",
    "years": [2022, 2023, 2024, 2025],
    "frequency": 7,
    "tags": ["segmentation"]
  },
  {
    "question": "Explain logical, linear and physical address.",
    "subject": "Computer organization and microprocessor",
    "type": "PYQ",
    "years": [2022],
    "frequency": 1,
    "tags": ["addressing"]
  },
  {
    "question": "Explain descriptor types in 80386.",
    "subject": "Computer organization and microprocessor",
    "type": "PYQ",
    "years": [2022, 2023, 2024],
    "frequency": 6,
    "tags": ["descriptors"]
  },
  {
    "question": "Explain GDTR, LDTR and IDTR.",
    "subject": "Computer organization and microprocessor",
    "type": "PYQ",
    "years": [2022, 2023, 2024],
    "frequency": 6,
    "tags": ["registers"]
  },
  {
    "question": "Explain general descriptor and selector format.",
    "subject": "Computer organization and microprocessor",
    "type": "PYQ",
    "years": [2022, 2023, 2024],
    "frequency": 6,
    "tags": ["descriptor"]
  },
  {
    "question": "Explain protection mechanism in 80386.",
    "subject": "Computer organization and microprocessor",
    "type": "PYQ",
    "years": [2022, 2023, 2024, 2025],
    "frequency": 8,
    "tags": ["protection"]
  },
  {
    "question": "Explain CPL, DPL, RPL and IOPL.",
    "subject": "Computer organization and microprocessor",
    "type": "PYQ",
    "years": [2022, 2023, 2024, 2025],
    "frequency": 7,
    "tags": ["privilege levels"]
  },
  {
    "question": "Explain privilege instructions.",
    "subject": "Computer organization and microprocessor",
    "type": "PYQ",
    "years": [2022, 2023, 2024, 2025],
    "frequency": 6,
    "tags": ["instructions"]
  },
  {
    "question": "Explain call gate and its use.",
    "subject": "Computer organization and microprocessor",
    "type": "PYQ",
    "years": [2022, 2023, 2024, 2025],
    "frequency": 6,
    "tags": ["call gate"]
  },
  {
    "question": "Explain task state segment (TSS).",
    "subject": "Computer organization and microprocessor",
    "type": "PYQ",
    "years": [2022, 2023, 2024, 2025],
    "frequency": 7,
    "tags": ["TSS"]
  },
  {
    "question": "Explain task switching in 80386.",
    "subject": "Computer organization and microprocessor",
    "type": "PYQ",
    "years": [2022, 2023, 2024, 2025],
    "frequency": 5,
    "tags": ["task switching"]
  },
  {
    "question": "Explain virtual 8086 mode and its features.",
    "subject": "Computer organization and microprocessor",
    "type": "PYQ",
    "years": [2022, 2023, 2024, 2025],
    "frequency": 6,
    "tags": ["virtual mode"]
  },
  {
    "question": "Explain interrupt handling in 80386.",
    "subject": "Computer organization and microprocessor",
    "type": "PYQ",
    "years": [2022, 2023, 2024, 2025],
    "frequency": 6,
    "tags": ["interrupts"]
  },
  {
    "question": "Explain exceptions in 80386.",
    "subject": "Computer organization and microprocessor",
    "type": "PYQ",
    "years": [2022, 2023, 2024, 2025],
    "frequency": 6,
    "tags": ["exceptions"]
  },
  {
    "question": "Differentiate between microprocessor and microcontroller.",
    "subject": "Computer organization and microprocessor",
    "type": "PYQ",
    "years": [2022, 2023, 2024, 2025],
    "frequency": 5,
    "tags": ["comparison"]
  },
  {
    "question": "Explain architecture of a typical microcontroller.",
    "subject": "Computer organization and microprocessor",
    "type": "PYQ",
    "years": [2022, 2023, 2024, 2025],
    "frequency": 5,
    "tags": ["microcontroller"]
  },
  {
    "question": "Explain features of 8051 microcontroller.",
    "subject": "Computer organization and microprocessor",
    "type": "PYQ",
    "years": [2023, 2024],
    "frequency": 3,
    "tags": ["8051"]
  },
  {
    "question": "List applications of microcontrollers.",
    "subject": "Computer organization and microprocessor",
    "type": "PYQ",
    "years": [2023, 2024],
    "frequency": 2,
    "tags": ["applications"]
  }
]